depeche_db/__init__.py
depeche_db/__main__.py
depeche_db/_aggregated_stream.py
depeche_db/_aggregated_stream_reader.py
depeche_db/_compat.py
depeche_db/_exceptions.py
depeche_db/_executor.py
depeche_db/_factories.py
depeche_db/_interfaces.py
depeche_db/_message_handler.py
depeche_db/_message_store.py
depeche_db/_storage.py
depeche_db/_subscription.py
depeche_db/py.typed
depeche_db/event_sourcing/__init__.py
depeche_db/event_sourcing/aggregate_root.py
depeche_db/event_sourcing/repository.py
depeche_db/experimental/__init__.py
depeche_db/experimental/threaded_executor.py
depeche_db/tools/__init__.py
depeche_db/tools/async_pg_notification_listener.py
depeche_db/tools/db_lock_provider.py
depeche_db/tools/db_subscription_state_provider.py
depeche_db/tools/immem_subscription.py
depeche_db/tools/pg_notification_listener.py
depeche_db/tools/pydantic_message_serializer.py
depeche_db/tools/stream_name_partitioner.py
depeche_db-0.13.0.dist-info/METADATA
depeche_db-0.13.0.dist-info/WHEEL
depeche_db-0.13.0.dist-info/licenses/LICENSE
depeche_db-0.13.0.dist-info/RECORD
