Metadata-Version: 2.4
Name: depeche-db
Version: 0.13.0
Summary: A library for building event-based systems on top of PostgreSQL
Project-URL: Homepage, https://github.com/depeche-py/depeche-db
Project-URL: Repository, https://github.com/depeche-py/depeche-db
Project-URL: Documentation, https://depeche-py.github.io/depeche-db/
Project-URL: Changelog, https://depeche-py.github.io/depeche-db/CHANGELOG/
Author-email: Martin Vielsmaier <martin@vielsmaier.net>
License-Expression: MIT
License-File: LICENSE
Keywords: event sourcing,event store,event-driven,message store,postgresql,sqlalchemy
Classifier: Development Status :: 3 - Alpha
Classifier: Intended Audience :: Developers
Classifier: License :: OSI Approved :: MIT License
Classifier: Topic :: Database
Requires-Python: ~=3.9
Requires-Dist: asyncer<0.0.9,>=0.0.8
Requires-Dist: pals<0.4,>=0.3.5
Requires-Dist: sqlalchemy-utils<0.42,>=0.41.1
Requires-Dist: sqlalchemy>=1.4.30
Provides-Extra: psycopg
Requires-Dist: psycopg>=3.2.1; extra == 'psycopg'
Provides-Extra: psycopg2
Requires-Dist: psycopg2~=2.9; extra == 'psycopg2'
